JushuitanDataCollection/__init__.py
JushuitanDataCollection/_login.py
JushuitanDataCollection/collector.py
JushuitanDataCollection/bi/bi.py
JushuitanDataCollection/bi/sales_theme_analysis.py
JushuitanDataCollection/bi/stock_analysis.py
JushuitanDataCollection/ss/_dict.py
JushuitanDataCollection/ss/report.py
JushuitanDataCollection/ss/ss.py
jushuitan_data_collection-2.0.7.dist-info/METADATA
jushuitan_data_collection-2.0.7.dist-info/WHEEL
jushuitan_data_collection-2.0.7.dist-info/licenses/LICENSE
jushuitan_data_collection-2.0.7.dist-info/RECORD
