Metadata-Version: 2.4
Name: jushuitan-data-collection
Version: 2.0.7
Summary: Jushuitan & Shengsuan Data Collection
Author: Martian Bugs
License-File: LICENSE
Requires-Python: >=3.12
Requires-Dist: browser-automation-launcher>=2.0.0
Requires-Dist: tenacity<10.0.0,>=9.1.2
